subsonic_connector/__init__.py
subsonic_connector/album.py
subsonic_connector/album_list.py
subsonic_connector/artist.py
subsonic_connector/artist_cover.py
subsonic_connector/artist_info.py
subsonic_connector/artist_list_item.py
subsonic_connector/artists.py
subsonic_connector/artists_initial.py
subsonic_connector/configuration.py
subsonic_connector/connector.py
subsonic_connector/default_config.py
subsonic_connector/genre.py
subsonic_connector/genres.py
subsonic_connector/internet_radio_station.py
subsonic_connector/internet_radio_stations.py
subsonic_connector/item.py
subsonic_connector/list_type.py
subsonic_connector/multi_value.py
subsonic_connector/playlist.py
subsonic_connector/playlist_entry.py
subsonic_connector/playlists.py
subsonic_connector/random_songs.py
subsonic_connector/response.py
subsonic_connector/search_result.py
subsonic_connector/similar_artist.py
subsonic_connector/similar_songs.py
subsonic_connector/song.py
subsonic_connector/starred.py
subsonic_connector/top_songs.py
subsonic_connector-0.3.10.dist-info/METADATA
subsonic_connector-0.3.10.dist-info/WHEEL
subsonic_connector-0.3.10.dist-info/licenses/LICENSE
subsonic_connector-0.3.10.dist-info/RECORD
