Metadata-Version: 2.4
Name: subsonic_connector
Version: 0.3.10
Summary: SubSonic Connector based on py-sonic
License-File: LICENSE
Author: GioF71
Author-email: giovanni.fulco@gmail.com
Requires-Python: >=3.9
Classifier: Programming Language :: Python :: 3
Classifier: License :: OSI Approved :: MIT License
Classifier: Operating System :: OS Independent
Requires-Dist: py-sonic (==1.0.3)
Project-URL: Bug Tracker, https://github.com/GioF71/subsonic-connector/issues
Project-URL: Homepage, https://github.com/GioF71/subsonic-connector
